README.md
setup.py
print_table/__init__.py
print_table/table.py
print_table.egg-info/PKG-INFO
print_table.egg-info/SOURCES.txt
print_table.egg-info/dependency_links.txt
print_table.egg-info/top_level.txt